top_choice/__init__.py
top_choice/lib/__init__.py
top_choice/lib/data_class.py
top_choice/lib/mapper_class.py
top_choice/lib/process_data.py
top_choice/lib/tools.py
top_choice/models/__init__.py
top_choice/models/base_model.py
top_choice/models/baseline_models.py
top_choice/models/feature_models.py
top_choice/models/latent_models.py
top_choice/models/main_models.py
top_choice-0.0.3.dist-info/LICENSE
top_choice-0.0.3.dist-info/METADATA
top_choice-0.0.3.dist-info/WHEEL
top_choice-0.0.3.dist-info/top_level.txt
top_choice-0.0.3.dist-info/RECORD
