Metadata-Version: 2.1
Name: top-choice
Version: 0.0.3
Summary: A package using topological data analysis to achieve robust product recommendations.
Home-page: https://github.com/bmwillett/topological-recommendations
Author: Brian Willett
Author-email: bmwillett1@gmail.com
License: UNKNOWN
Platform: UNKNOWN
Classifier: Programming Language :: Python :: 3
Classifier: License :: OSI Approved :: MIT License
Classifier: Operating System :: OS Independent
Requires-Python: >=3.6
Requires-Dist: numpy (==1.17.2)
Requires-Dist: pandas (==0.25.1)
Requires-Dist: matplotlib (==3.1.1)
Requires-Dist: scipy (==1.4.1)
Requires-Dist: Keras (==2.3.1)
Requires-Dist: tensorflow (==2.2.0)
Requires-Dist: scikit-learn (>=0.21.3)
Requires-Dist: predictor (==0.1.2)
Requires-Dist: adversary (==1.1.1)
Requires-Dist: pymapper (==0.1.0)
